log_config/__init__.py
log_config/log_config.py
log_config/run_log_config.py
log_config-2.1.0.dist-info/LICENSE
log_config-2.1.0.dist-info/METADATA
log_config-2.1.0.dist-info/WHEEL
log_config-2.1.0.dist-info/top_level.txt
log_config-2.1.0.dist-info/RECORD
