Metadata-Version: 2.1
Name: log_config
Version: 2.1.0
Summary: Provide a function for anyone who want to configure log parameters easily, just call init_log_config when your app start up, the you can use the module of logging which build-in python3 without any other configture. This module support TimeRotatingHandler, MultiProcessTimeRotatingHandler, RotatingFileHandler and SMTPHandler and You can change the configuration parameters according to your requirements.
Home-page: https://github.com/amazingcoderpro/log_config/
Author: Wu Charles
Author-email: wcadaydayup@163.com
Maintainer: Wu Charles
Maintainer-email: wcadaydayup@163.com
License: BSD License
Platform: all
Classifier: Development Status :: 5 - Production/Stable
Classifier: Operating System :: OS Independent
Classifier: Intended Audience :: Developers
Classifier: License :: OSI Approved :: BSD License
Classifier: Programming Language :: Python
Classifier: Programming Language :: Python :: Implementation
Classifier: Programming Language :: Python :: 2
Classifier: Programming Language :: Python :: 2.7
Classifier: Programming Language :: Python :: 3
Classifier: Programming Language :: Python :: 3.4
Classifier: Programming Language :: Python :: 3.5
Classifier: Programming Language :: Python :: 3.6
Classifier: Topic :: Software Development :: Libraries
License-File: LICENSE
